papermill_service/__init__.py
papermill_service/__main__.py
papermill_service/_version.py
papermill_service/app.py
papermill_service/config.py
papermill_service/executor.py
papermill_service-0.1.0.dist-info/LICENSE
papermill_service-0.1.0.dist-info/METADATA
papermill_service-0.1.0.dist-info/WHEEL
papermill_service-0.1.0.dist-info/entry_points.txt
papermill_service-0.1.0.dist-info/top_level.txt
papermill_service-0.1.0.dist-info/RECORD
